{
  "id": "a3dc1e9a-f282-42e2-8348-fcd4f89a2cb6",
  "prevId": "6839f9f4-61eb-4988-839c-5b18950fa29e",
  "version": "7",
  "dialect": "postgresql",
  "tables": {
    "public.sadra.nl_device": {
      "name": "sadra.nl_device",
      "schema": "",
      "columns": {
        "id": {
          "name": "id",
          "type": "serial",
          "primaryKey": true,
          "notNull": true
        },
        "created_at": {
          "name": "created_at",
          "type": "timestamp with time zone",
          "primaryKey": false,
          "notNull": true,
          "default": "CURRENT_TIMESTAMP"
        },
        "name": {
          "name": "name",
          "type": "varchar(256)",
          "primaryKey": false,
          "notNull": true
        },
        "device_id": {
          "name": "device_id",
          "type": "integer",
          "primaryKey": false,
          "notNull": true
        },
        "location_id": {
          "name": "location_id",
          "type": "integer",
          "primaryKey": false,
          "notNull": true
        },
        "register_interval": {
          "name": "register_interval",
          "type": "integer",
          "primaryKey": false,
          "notNull": true
        },
        "loudness_threshold": {
          "name": "loudness_threshold",
          "type": "integer",
          "primaryKey": false,
          "notNull": true
        }
      },
      "indexes": {
        "device_device_id_idx": {
          "name": "device_device_id_idx",
          "columns": [
            {
              "expression": "device_id",
              "isExpression": false,
              "asc": true,
              "nulls": "last"
            }
          ],
          "isUnique": false,
          "concurrently": false,
          "method": "btree",
          "with": {}
        },
        "device_location_id_idx": {
          "name": "device_location_id_idx",
          "columns": [
            {
              "expression": "location_id",
              "isExpression": false,
              "asc": true,
              "nulls": "last"
            }
          ],
          "isUnique": false,
          "concurrently": false,
          "method": "btree",
          "with": {}
        }
      },
      "foreignKeys": {
        "sadra.nl_device_location_id_sadra.nl_location_id_fk": {
          "name": "sadra.nl_device_location_id_sadra.nl_location_id_fk",
          "tableFrom": "sadra.nl_device",
          "tableTo": "sadra.nl_location",
          "columnsFrom": [
            "location_id"
          ],
          "columnsTo": [
            "id"
          ],
          "onDelete": "no action",
          "onUpdate": "no action"
        }
      },
      "compositePrimaryKeys": {},
      "uniqueConstraints": {
        "sadra.nl_device_device_id_unique": {
          "name": "sadra.nl_device_device_id_unique",
          "nullsNotDistinct": false,
          "columns": [
            "device_id"
          ]
        }
      },
      "policies": {},
      "checkConstraints": {},
      "isRLSEnabled": false
    },
    "public.sadra.nl_location": {
      "name": "sadra.nl_location",
      "schema": "",
      "columns": {
        "id": {
          "name": "id",
          "type": "serial",
          "primaryKey": true,
          "notNull": true
        },
        "created_at": {
          "name": "created_at",
          "type": "timestamp with time zone",
          "primaryKey": false,
          "notNull": true,
          "default": "CURRENT_TIMESTAMP"
        },
        "name": {
          "name": "name",
          "type": "varchar(256)",
          "primaryKey": false,
          "notNull": true
        },
        "location_name": {
          "name": "location_name",
          "type": "varchar(256)",
          "primaryKey": false,
          "notNull": true
        },
        "location_id": {
          "name": "location_id",
          "type": "integer",
          "primaryKey": false,
          "notNull": true
        }
      },
      "indexes": {
        "location_name_idx": {
          "name": "location_name_idx",
          "columns": [
            {
              "expression": "name",
              "isExpression": false,
              "asc": true,
              "nulls": "last"
            }
          ],
          "isUnique": false,
          "concurrently": false,
          "method": "btree",
          "with": {}
        },
        "location_id_idx": {
          "name": "location_id_idx",
          "columns": [
            {
              "expression": "location_id",
              "isExpression": false,
              "asc": true,
              "nulls": "last"
            }
          ],
          "isUnique": false,
          "concurrently": false,
          "method": "btree",
          "with": {}
        }
      },
      "foreignKeys": {},
      "compositePrimaryKeys": {},
      "uniqueConstraints": {
        "sadra.nl_location_location_id_unique": {
          "name": "sadra.nl_location_location_id_unique",
          "nullsNotDistinct": false,
          "columns": [
            "location_id"
          ]
        }
      },
      "policies": {},
      "checkConstraints": {},
      "isRLSEnabled": false
    },
    "public.sadra.nl_reading": {
      "name": "sadra.nl_reading",
      "schema": "",
      "columns": {
        "id": {
          "name": "id",
          "type": "serial",
          "primaryKey": true,
          "notNull": true
        },
        "created_at": {
          "name": "created_at",
          "type": "timestamp with time zone",
          "primaryKey": false,
          "notNull": true,
          "default": "CURRENT_TIMESTAMP"
        },
        "value": {
          "name": "value",
          "type": "real",
          "primaryKey": false,
          "notNull": true
        },
        "sensor_id": {
          "name": "sensor_id",
          "type": "integer",
          "primaryKey": false,
          "notNull": true
        },
        "location_id": {
          "name": "location_id",
          "type": "integer",
          "primaryKey": false,
          "notNull": true
        },
        "device_id": {
          "name": "device_id",
          "type": "integer",
          "primaryKey": false,
          "notNull": true
        }
      },
      "indexes": {
        "reading_sensor_id_idx": {
          "name": "reading_sensor_id_idx",
          "columns": [
            {
              "expression": "sensor_id",
              "isExpression": false,
              "asc": true,
              "nulls": "last"
            }
          ],
          "isUnique": false,
          "concurrently": false,
          "method": "btree",
          "with": {}
        },
        "reading_location_id_idx": {
          "name": "reading_location_id_idx",
          "columns": [
            {
              "expression": "location_id",
              "isExpression": false,
              "asc": true,
              "nulls": "last"
            }
          ],
          "isUnique": false,
          "concurrently": false,
          "method": "btree",
          "with": {}
        },
        "reading_device_id_idx": {
          "name": "reading_device_id_idx",
          "columns": [
            {
              "expression": "device_id",
              "isExpression": false,
              "asc": true,
              "nulls": "last"
            }
          ],
          "isUnique": false,
          "concurrently": false,
          "method": "btree",
          "with": {}
        }
      },
      "foreignKeys": {
        "sadra.nl_reading_sensor_id_sadra.nl_sensor_id_fk": {
          "name": "sadra.nl_reading_sensor_id_sadra.nl_sensor_id_fk",
          "tableFrom": "sadra.nl_reading",
          "tableTo": "sadra.nl_sensor",
          "columnsFrom": [
            "sensor_id"
          ],
          "columnsTo": [
            "id"
          ],
          "onDelete": "no action",
          "onUpdate": "no action"
        },
        "sadra.nl_reading_location_id_sadra.nl_location_id_fk": {
          "name": "sadra.nl_reading_location_id_sadra.nl_location_id_fk",
          "tableFrom": "sadra.nl_reading",
          "tableTo": "sadra.nl_location",
          "columnsFrom": [
            "location_id"
          ],
          "columnsTo": [
            "id"
          ],
          "onDelete": "no action",
          "onUpdate": "no action"
        },
        "sadra.nl_reading_device_id_sadra.nl_device_id_fk": {
          "name": "sadra.nl_reading_device_id_sadra.nl_device_id_fk",
          "tableFrom": "sadra.nl_reading",
          "tableTo": "sadra.nl_device",
          "columnsFrom": [
            "device_id"
          ],
          "columnsTo": [
            "id"
          ],
          "onDelete": "no action",
          "onUpdate": "no action"
        }
      },
      "compositePrimaryKeys": {},
      "uniqueConstraints": {},
      "policies": {},
      "checkConstraints": {},
      "isRLSEnabled": false
    },
    "public.sadra.nl_recording": {
      "name": "sadra.nl_recording",
      "schema": "",
      "columns": {
        "id": {
          "name": "id",
          "type": "serial",
          "primaryKey": true,
          "notNull": true
        },
        "created_at": {
          "name": "created_at",
          "type": "timestamp with time zone",
          "primaryKey": false,
          "notNull": true,
          "default": "CURRENT_TIMESTAMP"
        },
        "location_id": {
          "name": "location_id",
          "type": "integer",
          "primaryKey": false,
          "notNull": true
        },
        "device_id": {
          "name": "device_id",
          "type": "integer",
          "primaryKey": false,
          "notNull": true
        },
        "file_name": {
          "name": "file_name",
          "type": "varchar(256)",
          "primaryKey": false,
          "notNull": true
        },
        "file": {
          "name": "file",
          "type": "bytea",
          "primaryKey": false,
          "notNull": true
        }
      },
      "indexes": {
        "recording_location_id_idx": {
          "name": "recording_location_id_idx",
          "columns": [
            {
              "expression": "location_id",
              "isExpression": false,
              "asc": true,
              "nulls": "last"
            }
          ],
          "isUnique": false,
          "concurrently": false,
          "method": "btree",
          "with": {}
        },
        "recording_device_id_idx": {
          "name": "recording_device_id_idx",
          "columns": [
            {
              "expression": "device_id",
              "isExpression": false,
              "asc": true,
              "nulls": "last"
            }
          ],
          "isUnique": false,
          "concurrently": false,
          "method": "btree",
          "with": {}
        }
      },
      "foreignKeys": {
        "sadra.nl_recording_location_id_sadra.nl_location_id_fk": {
          "name": "sadra.nl_recording_location_id_sadra.nl_location_id_fk",
          "tableFrom": "sadra.nl_recording",
          "tableTo": "sadra.nl_location",
          "columnsFrom": [
            "location_id"
          ],
          "columnsTo": [
            "id"
          ],
          "onDelete": "no action",
          "onUpdate": "no action"
        },
        "sadra.nl_recording_device_id_sadra.nl_device_id_fk": {
          "name": "sadra.nl_recording_device_id_sadra.nl_device_id_fk",
          "tableFrom": "sadra.nl_recording",
          "tableTo": "sadra.nl_device",
          "columnsFrom": [
            "device_id"
          ],
          "columnsTo": [
            "id"
          ],
          "onDelete": "no action",
          "onUpdate": "no action"
        }
      },
      "compositePrimaryKeys": {},
      "uniqueConstraints": {},
      "policies": {},
      "checkConstraints": {},
      "isRLSEnabled": false
    },
    "public.sadra.nl_sensor": {
      "name": "sadra.nl_sensor",
      "schema": "",
      "columns": {
        "id": {
          "name": "id",
          "type": "serial",
          "primaryKey": true,
          "notNull": true
        },
        "created_at": {
          "name": "created_at",
          "type": "timestamp with time zone",
          "primaryKey": false,
          "notNull": true,
          "default": "CURRENT_TIMESTAMP"
        },
        "name": {
          "name": "name",
          "type": "varchar(256)",
          "primaryKey": false,
          "notNull": true
        },
        "unit": {
          "name": "unit",
          "type": "varchar(256)",
          "primaryKey": false,
          "notNull": true
        }
      },
      "indexes": {
        "sensor_name_idx": {
          "name": "sensor_name_idx",
          "columns": [
            {
              "expression": "name",
              "isExpression": false,
              "asc": true,
              "nulls": "last"
            }
          ],
          "isUnique": false,
          "concurrently": false,
          "method": "btree",
          "with": {}
        }
      },
      "foreignKeys": {},
      "compositePrimaryKeys": {},
      "uniqueConstraints": {},
      "policies": {},
      "checkConstraints": {},
      "isRLSEnabled": false
    },
    "public.sadra.nl_sensors_to_devices": {
      "name": "sadra.nl_sensors_to_devices",
      "schema": "",
      "columns": {
        "sensor_id": {
          "name": "sensor_id",
          "type": "integer",
          "primaryKey": false,
          "notNull": true
        },
        "device_id": {
          "name": "device_id",
          "type": "integer",
          "primaryKey": false,
          "notNull": true
        }
      },
      "indexes": {
        "sensors_to_devices_sensor_id_idx": {
          "name": "sensors_to_devices_sensor_id_idx",
          "columns": [
            {
              "expression": "sensor_id",
              "isExpression": false,
              "asc": true,
              "nulls": "last"
            }
          ],
          "isUnique": false,
          "concurrently": false,
          "method": "btree",
          "with": {}
        },
        "sensors_to_devices_device_id_idx": {
          "name": "sensors_to_devices_device_id_idx",
          "columns": [
            {
              "expression": "device_id",
              "isExpression": false,
              "asc": true,
              "nulls": "last"
            }
          ],
          "isUnique": false,
          "concurrently": false,
          "method": "btree",
          "with": {}
        }
      },
      "foreignKeys": {
        "sadra.nl_sensors_to_devices_sensor_id_sadra.nl_sensor_id_fk": {
          "name": "sadra.nl_sensors_to_devices_sensor_id_sadra.nl_sensor_id_fk",
          "tableFrom": "sadra.nl_sensors_to_devices",
          "tableTo": "sadra.nl_sensor",
          "columnsFrom": [
            "sensor_id"
          ],
          "columnsTo": [
            "id"
          ],
          "onDelete": "no action",
          "onUpdate": "no action"
        },
        "sadra.nl_sensors_to_devices_device_id_sadra.nl_device_id_fk": {
          "name": "sadra.nl_sensors_to_devices_device_id_sadra.nl_device_id_fk",
          "tableFrom": "sadra.nl_sensors_to_devices",
          "tableTo": "sadra.nl_device",
          "columnsFrom": [
            "device_id"
          ],
          "columnsTo": [
            "id"
          ],
          "onDelete": "no action",
          "onUpdate": "no action"
        }
      },
      "compositePrimaryKeys": {
        "sadra.nl_sensors_to_devices_sensor_id_device_id_pk": {
          "name": "sadra.nl_sensors_to_devices_sensor_id_device_id_pk",
          "columns": [
            "sensor_id",
            "device_id"
          ]
        }
      },
      "uniqueConstraints": {},
      "policies": {},
      "checkConstraints": {},
      "isRLSEnabled": false
    },
    "public.trading_bot_account": {
      "name": "trading_bot_account",
      "schema": "",
      "columns": {
        "id": {
          "name": "id",
          "type": "serial",
          "primaryKey": true,
          "notNull": true
        },
        "created_at": {
          "name": "created_at",
          "type": "timestamp with time zone",
          "primaryKey": false,
          "notNull": true,
          "default": "CURRENT_TIMESTAMP"
        },
        "server": {
          "name": "server",
          "type": "varchar(256)",
          "primaryKey": false,
          "notNull": true
        },
        "login": {
          "name": "login",
          "type": "varchar(256)",
          "primaryKey": false,
          "notNull": true
        },
        "password": {
          "name": "password",
          "type": "varchar(256)",
          "primaryKey": false,
          "notNull": true
        },
        "enabled": {
          "name": "enabled",
          "type": "boolean",
          "primaryKey": false,
          "notNull": true,
          "default": false
        },
        "config_name": {
          "name": "config_name",
          "type": "varchar(256)",
          "primaryKey": false,
          "notNull": false
        }
      },
      "indexes": {},
      "foreignKeys": {},
      "compositePrimaryKeys": {},
      "uniqueConstraints": {},
      "policies": {},
      "checkConstraints": {},
      "isRLSEnabled": false
    }
  },
  "enums": {},
  "schemas": {},
  "sequences": {},
  "roles": {},
  "policies": {},
  "views": {},
  "_meta": {
    "columns": {},
    "schemas": {},
    "tables": {}
  }
}